{"name":"vide","className":"ModuleScript","filePaths":["src\\init.luau","default.project.json"],"children":[{"name":"action","className":"ModuleScript","filePaths":["src\\action.luau"]},{"name":"apply","className":"ModuleScript","filePaths":["src\\apply.luau"]},{"name":"batch","className":"ModuleScript","filePaths":["src\\batch.luau"]},{"name":"bind","className":"ModuleScript","filePaths":["src\\bind.luau"]},{"name":"changed","className":"ModuleScript","filePaths":["src\\changed.luau"]},{"name":"cleanup","className":"ModuleScript","filePaths":["src\\cleanup.luau"]},{"name":"context","className":"ModuleScript","filePaths":["src\\context.luau"]},{"name":"create","className":"ModuleScript","filePaths":["src\\create.luau"]},{"name":"defaults","className":"ModuleScript","filePaths":["src\\defaults.luau"]},{"name":"derive","className":"ModuleScript","filePaths":["src\\derive.luau"]},{"name":"effect","className":"ModuleScript","filePaths":["src\\effect.luau"]},{"name":"flags","className":"ModuleScript","filePaths":["src\\flags.luau"]},{"name":"graph","className":"ModuleScript","filePaths":["src\\graph.luau"]},{"name":"maps","className":"ModuleScript","filePaths":["src\\maps.luau"]},{"name":"mount","className":"ModuleScript","filePaths":["src\\mount.luau"]},{"name":"read","className":"ModuleScript","filePaths":["src\\read.luau"]},{"name":"root","className":"ModuleScript","filePaths":["src\\root.luau"]},{"name":"show","className":"ModuleScript","filePaths":["src\\show.luau"]},{"name":"source","className":"ModuleScript","filePaths":["src\\source.luau"]},{"name":"spring","className":"ModuleScript","filePaths":["src\\spring.luau"]},{"name":"switch","className":"ModuleScript","filePaths":["src\\switch.luau"]},{"name":"throw","className":"ModuleScript","filePaths":["src\\throw.luau"]},{"name":"untrack","className":"ModuleScript","filePaths":["src\\untrack.luau"]}]}